[
  {
    "id": "workshop-overview",
    "name": "Main Repair Bay",
    "technique": "Workshop Photo",
    "description": "Inside Piri's Ding Repair, where boards are inspected, repaired, and prepared for the next swell.",
    "image": "/images/piri-workshop-1.png",
    "colors": ["Natural Light", "Ocean Blue", "Workshop Tones"],
    "timeToComplete": "Quote on request",
    "additionalCost": "Varies by damage"
  },
  {
    "id": "tools-materials",
    "name": "Tools & Materials",
    "technique": "Workshop Photo",
    "description": "Shelves stocked with repair supplies and ready-to-work boards.",
    "image": "/images/piri-workshop-2.png",
    "colors": ["Green", "Blue", "Neutral"],
    "timeToComplete": "Quote on request",
    "additionalCost": "Varies by damage"
  },
  {
    "id": "wall-display",
    "name": "Boards & Workshop Wall",
    "technique": "Workshop Photo",
    "description": "A look at the boards, references, and working atmosphere inside the repair space.",
    "image": "/images/piri-workshop-3.png",
    "colors": ["Blue", "White", "Sand"],
    "timeToComplete": "Quote on request",
    "additionalCost": "Varies by damage"
  }
]