[
  {
    "id": "workshop-overview",
    "name": "Main Repair Bay",
    "technique": "Workshop Photo",
    "description": "Inside Piri's Ding Repair, where boards are inspected, repaired, and prepared for the next swell.",
    "image": "/images/piri-workshop-1.png",
    "colors": ["Natural Light", "Ocean Blue", "Workshop Tones"],
    "timeToComplete": "Quote on request",
    "additionalCost": "Varies by damage"
  },
  {
    "id": "tee-shirt-1",
    "name": "Piri Tee-shirt Front Print",
    "technique": "Accessories Photo",
    "description": "Official Piri's Ding Repair tee-shirt. Price: $15.",
    "image": "/images/piri-shirt-1.png",
    "colors": ["Black", "White"],
    "timeToComplete": "In stock",
    "additionalCost": "$15"
  },
  {
    "id": "tee-shirt-2",
    "name": "Piri Tee-shirt Closeup",
    "technique": "Accessories Photo",
    "description": "Closeup of logo print version available in shop.",
    "image": "/images/piri-shirt-2.png",
    "colors": ["Black", "White"],
    "timeToComplete": "In stock",
    "additionalCost": "$15"
  },
  {
    "id": "tank-top-1",
    "name": "Piri Tank Top",
    "technique": "Accessories Photo",
    "description": "Sleeveless version with front chest logo. Price: $15.",
    "image": "/images/piri-shirt-3.png",
    "colors": ["Black", "White"],
    "timeToComplete": "In stock",
    "additionalCost": "$15"
  },
  {
    "id": "tee-shirt-back-1",
    "name": "Piri Tee-shirt Back Print",
    "technique": "Accessories Photo",
    "description": "Large back print version with Punta Roca design.",
    "image": "/images/piri-shirt-4.png",
    "colors": ["Black", "White", "Blue"],
    "timeToComplete": "In stock",
    "additionalCost": "$15"
  },
  {
    "id": "tank-top-back-1",
    "name": "Piri Tank Top Back Print",
    "technique": "Accessories Photo",
    "description": "Large back print tank top version. Price: $15.",
    "image": "/images/piri-shirt-5.png",
    "colors": ["Black", "White", "Blue"],
    "timeToComplete": "In stock",
    "additionalCost": "$15"
  },
  {
    "id": "tools-materials",
    "name": "Tools & Materials",
    "technique": "Workshop Photo",
    "description": "Shelves stocked with repair supplies and ready-to-work boards.",
    "image": "/images/piri-workshop-2.png",
    "colors": ["Green", "Blue", "Neutral"],
    "timeToComplete": "Quote on request",
    "additionalCost": "Varies by damage"
  },
  {
    "id": "wall-display",
    "name": "Boards & Workshop Wall",
    "technique": "Workshop Photo",
    "description": "A look at the boards, references, and working atmosphere inside the repair space.",
    "image": "/images/piri-workshop-3.png",
    "colors": ["Blue", "White", "Sand"],
    "timeToComplete": "Quote on request",
    "additionalCost": "Varies by damage"
  }
]